ipython_profile.py
ipython_profile-0.1.0.dist-info/entry_points.txt
ipython_profile-0.1.0.dist-info/LICENSE
ipython_profile-0.1.0.dist-info/WHEEL
ipython_profile-0.1.0.dist-info/METADATA
ipython_profile-0.1.0.dist-info/RECORD
