Metadata-Version: 2.1
Name: ipython-profile
Version: 0.1.0
Summary: An opinionated iPython profile for interactive development
License: MIT
Author: Seva Zhidkov
Author-email: zhidkovseva@gmail.com
Requires-Python: >=3.8,<4.0
Classifier: License :: OSI Approved :: MIT License
Classifier: Programming Language :: Python :: 3
Classifier: Programming Language :: Python :: 3.10
Classifier: Programming Language :: Python :: 3.8
Classifier: Programming Language :: Python :: 3.9
Requires-Dist: click (>=8.0.3,<9.0.0)
Requires-Dist: ipython (>=8.0.1,<9.0.0)
Requires-Dist: ipython-autoimport (>=0.3,<0.4)
Requires-Dist: requests (>=2.27.1,<3.0.0)
